xrmath/__init__.py
xrmath/xrmath.py
xrmath-0.0.4.dist-info/METADATA
xrmath-0.0.4.dist-info/WHEEL
xrmath-0.0.4.dist-info/license
xrmath-0.0.4.dist-info/top_level.txt
xrmath-0.0.4.dist-info/RECORD
